{
  "name": "admin",
  "routes": [
    {
      "method": "GET",
      "path": "/enabled-modules",
      "auth": true,
      "summary": "GET /enabled-modules",
      "validationName": "\"/enabled-modules\"",
      "controllerName": "getEnabledModules"
    },
    {
      "method": "GET",
      "path": "/analytics-modules",
      "auth": true,
      "summary": "GET /analytics-modules",
      "validationName": "\"/analytics-modules\"",
      "controllerName": "getAnalyticsModules"
    },
    {
      "method": "POST",
      "path": "/modules",
      "auth": true,
      "summary": "POST /modules",
      "validationName": "\"/modules\"",
      "controllerName": "getModules"
    },
    {
      "method": "GET",
      "path": "/modules",
      "auth": true,
      "summary": "GET /modules",
      "validationName": "\"/modules\"",
      "controllerName": "getModules"
    },
    {
      "method": "GET",
      "path": "/projects",
      "auth": true,
      "summary": "GET /projects",
      "validationName": "\"/projects\"",
      "controllerName": "getProjects"
    },
    {
      "method": "GET",
      "path": "/module/:name",
      "auth": true,
      "summary": "GET /module/:name",
      "validationName": "\"/modules/:name/toggle-analytics\"",
      "controllerName": "toggleUseAnalytics",
      "body": {
        "type": "object",
        "properties": {}
      }
    },
    {
      "method": "PATCH",
      "path": "/module/:name",
      "auth": true,
      "summary": "PATCH /module/:name",
      "validationName": "\"/modules/:name/toggle-analytics\"",
      "controllerName": "toggleUseAnalytics",
      "body": {
        "type": "object",
        "properties": {}
      }
    },
    {
      "method": "DELETE",
      "path": "/module/:name",
      "auth": true,
      "summary": "DELETE /module/:name",
      "validationName": "\"/modules/:name/toggle-analytics\"",
      "controllerName": "toggleUseAnalytics",
      "body": {
        "type": "object",
        "properties": {}
      }
    },
    {
      "method": "PATCH",
      "path": "/modules/:name/toggle-analytics",
      "auth": true,
      "summary": "PATCH /modules/:name/toggle-analytics",
      "validationName": "\"/modules/:name/toggle-analytics\"",
      "controllerName": "toggleUseAnalytics"
    }
  ],
  "label": {
    "tr": "admin",
    "en": "admin",
    "de": "admin",
    "pl": "admin",
    "fr": "admin",
    "es": "admin"
  },
  "icon": "box",
  "roles": [
    "admin"
  ],
  "useAnalytics": false,
  "language": "en",
  "version": "1.0.28",
  "updatedBy": {
    "username": "Orhan Güzel",
    "commitHash": "8da4e9a8d6a12db1d202422029178363f046a7c0"
  },
  "commitHash": "8da4e9a8d6a12db1d202422029178363f046a7c0",
  "lastUpdatedAt": "2025-06-19T11:19:40.042Z",
  "history": [
    {
      "version": "1.0.1",
      "by": "Orhan Güzel",
      "commitHash": "8da4e9a8d6a12db1d202422029178363f046a7c0",
      "date": "2025-06-18T21:01:18.121Z",
      "note": "Meta versiyonu {version} olarak {by} tarafından yükseltildi."
    },
    {
      "version": "1.0.2",
      "by": "Orhan Güzel",
      "commitHash": "8da4e9a8d6a12db1d202422029178363f046a7c0",
      "date": "2025-06-18T21:01:29.001Z",
      "note": "Meta versiyonu {version} olarak {by} tarafından yükseltildi."
    },
    {
      "version": "1.0.3",
      "by": "Orhan Güzel",
      "commitHash": "8da4e9a8d6a12db1d202422029178363f046a7c0",
      "date": "2025-06-18T21:01:46.518Z",
      "note": "Meta versiyonu {version} olarak {by} tarafından yükseltildi."
    },
    {
      "version": "1.0.4",
      "by": "Orhan Güzel",
      "commitHash": "8da4e9a8d6a12db1d202422029178363f046a7c0",
      "date": "2025-06-18T21:01:49.879Z",
      "note": "Meta versiyonu {version} olarak {by} tarafından yükseltildi."
    },
    {
      "version": "1.0.5",
      "by": "Orhan Güzel",
      "commitHash": "8da4e9a8d6a12db1d202422029178363f046a7c0",
      "date": "2025-06-18T21:19:43.831Z",
      "note": "Meta versiyonu {version} olarak {by} tarafından yükseltildi."
    },
    {
      "version": "1.0.6",
      "by": "Orhan Güzel",
      "commitHash": "8da4e9a8d6a12db1d202422029178363f046a7c0",
      "date": "2025-06-18T21:19:57.480Z",
      "note": "Meta versiyonu {version} olarak {by} tarafından yükseltildi."
    },
    {
      "version": "1.0.7",
      "by": "Orhan Güzel",
      "commitHash": "8da4e9a8d6a12db1d202422029178363f046a7c0",
      "date": "2025-06-18T21:20:19.732Z",
      "note": "Meta versiyonu {version} olarak {by} tarafından yükseltildi."
    },
    {
      "version": "1.0.8",
      "by": "Orhan Güzel",
      "commitHash": "8da4e9a8d6a12db1d202422029178363f046a7c0",
      "date": "2025-06-18T21:20:24.218Z",
      "note": "Meta versiyonu {version} olarak {by} tarafından yükseltildi."
    },
    {
      "version": "1.0.9",
      "by": "Orhan Güzel",
      "commitHash": "8da4e9a8d6a12db1d202422029178363f046a7c0",
      "date": "2025-06-18T21:50:39.460Z",
      "note": "Meta versiyonu {version} olarak {by} tarafından yükseltildi."
    },
    {
      "version": "1.0.10",
      "by": "Orhan Güzel",
      "commitHash": "8da4e9a8d6a12db1d202422029178363f046a7c0",
      "date": "2025-06-18T21:50:49.736Z",
      "note": "Meta versiyonu {version} olarak {by} tarafından yükseltildi."
    },
    {
      "version": "1.0.11",
      "by": "Orhan Güzel",
      "commitHash": "8da4e9a8d6a12db1d202422029178363f046a7c0",
      "date": "2025-06-18T21:51:07.747Z",
      "note": "Meta versiyonu {version} olarak {by} tarafından yükseltildi."
    },
    {
      "version": "1.0.12",
      "by": "Orhan Güzel",
      "commitHash": "8da4e9a8d6a12db1d202422029178363f046a7c0",
      "date": "2025-06-18T21:51:11.236Z",
      "note": "Meta versiyonu {version} olarak {by} tarafından yükseltildi."
    },
    {
      "version": "1.0.13",
      "by": "Orhan Güzel",
      "commitHash": "8da4e9a8d6a12db1d202422029178363f046a7c0",
      "date": "2025-06-18T22:03:00.343Z",
      "note": "Meta versiyonu {version} olarak {by} tarafından yükseltildi."
    },
    {
      "version": "1.0.14",
      "by": "Orhan Güzel",
      "commitHash": "8da4e9a8d6a12db1d202422029178363f046a7c0",
      "date": "2025-06-18T22:03:12.323Z",
      "note": "Meta versiyonu {version} olarak {by} tarafından yükseltildi."
    },
    {
      "version": "1.0.15",
      "by": "Orhan Güzel",
      "commitHash": "8da4e9a8d6a12db1d202422029178363f046a7c0",
      "date": "2025-06-18T22:04:04.931Z",
      "note": "Meta versiyonu {version} olarak {by} tarafından yükseltildi."
    },
    {
      "version": "1.0.16",
      "by": "Orhan Güzel",
      "commitHash": "8da4e9a8d6a12db1d202422029178363f046a7c0",
      "date": "2025-06-18T22:04:14.969Z",
      "note": "Meta versiyonu {version} olarak {by} tarafından yükseltildi."
    },
    {
      "version": "1.0.17",
      "by": "Orhan Güzel",
      "commitHash": "8da4e9a8d6a12db1d202422029178363f046a7c0",
      "date": "2025-06-19T00:11:35.327Z",
      "note": "Meta versiyonu {version} olarak {by} tarafından yükseltildi."
    },
    {
      "version": "1.0.18",
      "by": "Orhan Güzel",
      "commitHash": "8da4e9a8d6a12db1d202422029178363f046a7c0",
      "date": "2025-06-19T00:11:44.305Z",
      "note": "Meta versiyonu {version} olarak {by} tarafından yükseltildi."
    },
    {
      "version": "1.0.19",
      "by": "Orhan Güzel",
      "commitHash": "8da4e9a8d6a12db1d202422029178363f046a7c0",
      "date": "2025-06-19T00:32:09.429Z",
      "note": "Meta versiyonu {version} olarak {by} tarafından yükseltildi."
    },
    {
      "version": "1.0.20",
      "by": "Orhan Güzel",
      "commitHash": "8da4e9a8d6a12db1d202422029178363f046a7c0",
      "date": "2025-06-19T00:32:20.406Z",
      "note": "Meta versiyonu {version} olarak {by} tarafından yükseltildi."
    },
    {
      "version": "1.0.21",
      "by": "Orhan Güzel",
      "commitHash": "8da4e9a8d6a12db1d202422029178363f046a7c0",
      "date": "2025-06-19T01:22:52.197Z",
      "note": "Meta versiyonu {version} olarak {by} tarafından yükseltildi."
    },
    {
      "version": "1.0.22",
      "by": "Orhan Güzel",
      "commitHash": "8da4e9a8d6a12db1d202422029178363f046a7c0",
      "date": "2025-06-19T01:23:07.178Z",
      "note": "Meta versiyonu {version} olarak {by} tarafından yükseltildi."
    },
    {
      "version": "1.0.23",
      "by": "Orhan Güzel",
      "commitHash": "8da4e9a8d6a12db1d202422029178363f046a7c0",
      "date": "2025-06-19T11:02:49.253Z",
      "note": "Meta versiyonu {version} olarak {by} tarafından yükseltildi."
    },
    {
      "version": "1.0.24",
      "by": "Orhan Güzel",
      "commitHash": "8da4e9a8d6a12db1d202422029178363f046a7c0",
      "date": "2025-06-19T11:02:59.613Z",
      "note": "Meta versiyonu {version} olarak {by} tarafından yükseltildi."
    },
    {
      "version": "1.0.25",
      "by": "Orhan Güzel",
      "commitHash": "8da4e9a8d6a12db1d202422029178363f046a7c0",
      "date": "2025-06-19T11:07:10.081Z",
      "note": "Meta versiyonu {version} olarak {by} tarafından yükseltildi."
    },
    {
      "version": "1.0.26",
      "by": "Orhan Güzel",
      "commitHash": "8da4e9a8d6a12db1d202422029178363f046a7c0",
      "date": "2025-06-19T11:07:17.399Z",
      "note": "Meta versiyonu {version} olarak {by} tarafından yükseltildi."
    },
    {
      "version": "1.0.27",
      "by": "Orhan Güzel",
      "commitHash": "8da4e9a8d6a12db1d202422029178363f046a7c0",
      "date": "2025-06-19T11:19:30.897Z",
      "note": "Meta versiyonu {version} olarak {by} tarafından yükseltildi."
    },
    {
      "version": "1.0.28",
      "by": "Orhan Güzel",
      "commitHash": "8da4e9a8d6a12db1d202422029178363f046a7c0",
      "date": "2025-06-19T11:19:40.042Z",
      "note": "Meta versiyonu {version} olarak {by} tarafından yükseltildi."
    }
  ]
}