{
  "name": "dashboard",
  "routes": [
    {
      "method": "GET",
      "path": "/",
      "auth": true,
      "summary": "GET /",
      "validationName": "\"/\"",
      "controllerName": "getDashboardStats",
      "body": {
        "type": "object",
        "properties": {}
      }
    },
    {
      "method": "GET",
      "path": "/charts/orders",
      "auth": true,
      "summary": "GET /charts/orders",
      "validationName": "\"/daily-overview\"",
      "controllerName": "getDailyOverview"
    },
    {
      "method": "GET",
      "path": "/charts/revenue",
      "auth": true,
      "summary": "GET /charts/revenue",
      "validationName": "\"/daily-overview\"",
      "controllerName": "getDailyOverview"
    },
    {
      "method": "GET",
      "path": "/reports/top-products",
      "auth": true,
      "summary": "GET /reports/top-products",
      "validationName": "\"/daily-overview\"",
      "controllerName": "getDailyOverview"
    },
    {
      "method": "GET",
      "path": "/reports/user-roles",
      "auth": true,
      "summary": "GET /reports/user-roles",
      "validationName": "\"/daily-overview\"",
      "controllerName": "getDailyOverview"
    },
    {
      "method": "GET",
      "path": "/daily-overview",
      "auth": true,
      "summary": "GET /daily-overview",
      "validationName": "\"/daily-overview\"",
      "controllerName": "getDailyOverview"
    },
    {
      "method": "GET",
      "path": "/logs",
      "auth": true,
      "summary": "GET /logs"
    }
  ],
  "label": {
    "tr": "dashboard",
    "en": "dashboard",
    "de": "dashboard",
    "pl": "dashboard",
    "fr": "dashboard",
    "es": "dashboard"
  },
  "icon": "box",
  "roles": [
    "admin"
  ],
  "useAnalytics": false,
  "language": "en",
  "version": "1.0.1",
  "updatedBy": {
    "username": "Orhan Güzel",
    "commitHash": "769653ecb5b74af7ad3b0a3aa68f987ade5a9167"
  },
  "commitHash": "769653ecb5b74af7ad3b0a3aa68f987ade5a9167",
  "lastUpdatedAt": "2025-06-18T17:18:02.542Z",
  "history": [
    {
      "version": "1.0.1",
      "by": "Orhan Güzel",
      "commitHash": "769653ecb5b74af7ad3b0a3aa68f987ade5a9167",
      "date": "2025-06-18T17:18:02.542Z",
      "note": "Meta versiyonu {version} olarak {by} tarafından yükseltildi."
    }
  ]
}