{
  "name": "comment",
  "icon": "box",
  "roles": [
    "admin"
  ],
  "useAnalytics": false,
  "language": "en",
  "routes": [
    {
      "method": "POST",
      "path": "/",
      "auth": true,
      "summary": "POST /",
      "validationName": "\"admin\"",
      "controllerName": "\"moderator\")",
      "body": {
        "type": "object",
        "properties": {}
      }
    },
    {
      "method": "GET",
      "path": "/:type/:id",
      "auth": true,
      "summary": "GET /:type/:id",
      "validationName": "\"admin\"",
      "controllerName": "\"moderator\")"
    },
    {
      "method": "GET",
      "path": "/",
      "auth": true,
      "summary": "GET /",
      "validationName": "\"/\"",
      "controllerName": "getAllComments",
      "body": {
        "type": "object",
        "properties": {}
      }
    },
    {
      "method": "PUT",
      "path": "/:id/toggle",
      "auth": true,
      "summary": "PUT /:id/toggle"
    },
    {
      "method": "DELETE",
      "path": "/:id",
      "auth": true,
      "summary": "DELETE /:id"
    },
    {
      "method": "PUT",
      "path": "/:id/reply",
      "auth": true,
      "summary": "PUT /:id/reply"
    }
  ],
  "version": "1.0.1",
  "updatedBy": {
    "username": "Orhan Güzel",
    "commitHash": "2f91025ee6d70465b01704e36f0b80a355e576c7"
  },
  "commitHash": "2f91025ee6d70465b01704e36f0b80a355e576c7",
  "lastUpdatedAt": "2025-06-10T07:53:01.904Z",
  "history": [
    {
      "version": "1.0.1",
      "by": "Orhan Güzel",
      "commitHash": "2f91025ee6d70465b01704e36f0b80a355e576c7",
      "date": "2025-06-10T07:53:01.904Z",
      "note": "Meta auto-generated"
    }
  ]
}