{
  "name": "referencescategory",
  "routes": [
    {
      "method": "POST",
      "path": "/",
      "auth": true,
      "summary": "POST /",
      "validationName": "\"/\"",
      "controllerName": "getAllReferenceCategories",
      "pathPrefix": "category"
    },
    {
      "method": "GET",
      "path": "/",
      "auth": true,
      "summary": "GET /",
      "validationName": "\"/\"",
      "controllerName": "getAllReferenceCategories",
      "pathPrefix": "category"
    },
    {
      "method": "GET",
      "path": "/:id",
      "auth": true,
      "summary": "GET /:id",
      "pathPrefix": "category"
    },
    {
      "method": "DELETE",
      "path": "/:id",
      "auth": true,
      "summary": "DELETE /:id",
      "pathPrefix": "category"
    }
  ],
  "label": {
    "tr": "referencescategory",
    "en": "referencescategory",
    "de": "referencescategory",
    "pl": "referencescategory",
    "fr": "referencescategory",
    "es": "referencescategory"
  },
  "icon": "box",
  "roles": [
    "admin"
  ],
  "useAnalytics": false,
  "language": "en",
  "version": "1.0.41",
  "updatedBy": {
    "username": "Orhan Güzel",
    "commitHash": "8da4e9a8d6a12db1d202422029178363f046a7c0"
  },
  "commitHash": "8da4e9a8d6a12db1d202422029178363f046a7c0",
  "lastUpdatedAt": "2025-06-19T11:19:46.877Z",
  "history": [
    {
      "version": "1.0.1",
      "by": "Orhan Güzel",
      "commitHash": "8da4e9a8d6a12db1d202422029178363f046a7c0",
      "date": "2025-06-18T21:01:22.248Z",
      "note": "Meta versiyonu {version} olarak {by} tarafından yükseltildi."
    },
    {
      "version": "1.0.2",
      "by": "Orhan Güzel",
      "commitHash": "8da4e9a8d6a12db1d202422029178363f046a7c0",
      "date": "2025-06-18T21:01:24.638Z",
      "note": "Meta versiyonu {version} olarak {by} tarafından yükseltildi."
    },
    {
      "version": "1.0.3",
      "by": "Orhan Güzel",
      "commitHash": "8da4e9a8d6a12db1d202422029178363f046a7c0",
      "date": "2025-06-18T21:01:36.193Z",
      "note": "Meta versiyonu {version} olarak {by} tarafından yükseltildi."
    },
    {
      "version": "1.0.4",
      "by": "Orhan Güzel",
      "commitHash": "8da4e9a8d6a12db1d202422029178363f046a7c0",
      "date": "2025-06-18T21:01:47.267Z",
      "note": "Meta versiyonu {version} olarak {by} tarafından yükseltildi."
    },
    {
      "version": "1.0.5",
      "by": "Orhan Güzel",
      "commitHash": "8da4e9a8d6a12db1d202422029178363f046a7c0",
      "date": "2025-06-18T21:01:47.898Z",
      "note": "Meta versiyonu {version} olarak {by} tarafından yükseltildi."
    },
    {
      "version": "1.0.6",
      "by": "Orhan Güzel",
      "commitHash": "8da4e9a8d6a12db1d202422029178363f046a7c0",
      "date": "2025-06-18T21:01:52.735Z",
      "note": "Meta versiyonu {version} olarak {by} tarafından yükseltildi."
    },
    {
      "version": "1.0.7",
      "by": "Orhan Güzel",
      "commitHash": "8da4e9a8d6a12db1d202422029178363f046a7c0",
      "date": "2025-06-18T21:19:48.948Z",
      "note": "Meta versiyonu {version} olarak {by} tarafından yükseltildi."
    },
    {
      "version": "1.0.8",
      "by": "Orhan Güzel",
      "commitHash": "8da4e9a8d6a12db1d202422029178363f046a7c0",
      "date": "2025-06-18T21:19:51.982Z",
      "note": "Meta versiyonu {version} olarak {by} tarafından yükseltildi."
    },
    {
      "version": "1.0.9",
      "by": "Orhan Güzel",
      "commitHash": "8da4e9a8d6a12db1d202422029178363f046a7c0",
      "date": "2025-06-18T21:20:07.561Z",
      "note": "Meta versiyonu {version} olarak {by} tarafından yükseltildi."
    },
    {
      "version": "1.0.10",
      "by": "Orhan Güzel",
      "commitHash": "8da4e9a8d6a12db1d202422029178363f046a7c0",
      "date": "2025-06-18T21:20:20.715Z",
      "note": "Meta versiyonu {version} olarak {by} tarafından yükseltildi."
    },
    {
      "version": "1.0.11",
      "by": "Orhan Güzel",
      "commitHash": "8da4e9a8d6a12db1d202422029178363f046a7c0",
      "date": "2025-06-18T21:20:21.608Z",
      "note": "Meta versiyonu {version} olarak {by} tarafından yükseltildi."
    },
    {
      "version": "1.0.12",
      "by": "Orhan Güzel",
      "commitHash": "8da4e9a8d6a12db1d202422029178363f046a7c0",
      "date": "2025-06-18T21:20:28.312Z",
      "note": "Meta versiyonu {version} olarak {by} tarafından yükseltildi."
    },
    {
      "version": "1.0.13",
      "by": "Orhan Güzel",
      "commitHash": "8da4e9a8d6a12db1d202422029178363f046a7c0",
      "date": "2025-06-18T21:50:43.405Z",
      "note": "Meta versiyonu {version} olarak {by} tarafından yükseltildi."
    },
    {
      "version": "1.0.14",
      "by": "Orhan Güzel",
      "commitHash": "8da4e9a8d6a12db1d202422029178363f046a7c0",
      "date": "2025-06-18T21:50:45.720Z",
      "note": "Meta versiyonu {version} olarak {by} tarafından yükseltildi."
    },
    {
      "version": "1.0.15",
      "by": "Orhan Güzel",
      "commitHash": "8da4e9a8d6a12db1d202422029178363f046a7c0",
      "date": "2025-06-18T21:50:56.827Z",
      "note": "Meta versiyonu {version} olarak {by} tarafından yükseltildi."
    },
    {
      "version": "1.0.16",
      "by": "Orhan Güzel",
      "commitHash": "8da4e9a8d6a12db1d202422029178363f046a7c0",
      "date": "2025-06-18T21:51:08.473Z",
      "note": "Meta versiyonu {version} olarak {by} tarafından yükseltildi."
    },
    {
      "version": "1.0.17",
      "by": "Orhan Güzel",
      "commitHash": "8da4e9a8d6a12db1d202422029178363f046a7c0",
      "date": "2025-06-18T21:51:09.193Z",
      "note": "Meta versiyonu {version} olarak {by} tarafından yükseltildi."
    },
    {
      "version": "1.0.18",
      "by": "Orhan Güzel",
      "commitHash": "8da4e9a8d6a12db1d202422029178363f046a7c0",
      "date": "2025-06-18T21:51:14.090Z",
      "note": "Meta versiyonu {version} olarak {by} tarafından yükseltildi."
    },
    {
      "version": "1.0.19",
      "by": "Orhan Güzel",
      "commitHash": "8da4e9a8d6a12db1d202422029178363f046a7c0",
      "date": "2025-06-18T22:03:04.889Z",
      "note": "Meta versiyonu {version} olarak {by} tarafından yükseltildi."
    },
    {
      "version": "1.0.20",
      "by": "Orhan Güzel",
      "commitHash": "8da4e9a8d6a12db1d202422029178363f046a7c0",
      "date": "2025-06-18T22:03:07.602Z",
      "note": "Meta versiyonu {version} olarak {by} tarafından yükseltildi."
    },
    {
      "version": "1.0.21",
      "by": "Orhan Güzel",
      "commitHash": "8da4e9a8d6a12db1d202422029178363f046a7c0",
      "date": "2025-06-18T22:04:08.608Z",
      "note": "Meta versiyonu {version} olarak {by} tarafından yükseltildi."
    },
    {
      "version": "1.0.22",
      "by": "Orhan Güzel",
      "commitHash": "8da4e9a8d6a12db1d202422029178363f046a7c0",
      "date": "2025-06-18T22:04:10.752Z",
      "note": "Meta versiyonu {version} olarak {by} tarafından yükseltildi."
    },
    {
      "version": "1.0.23",
      "by": "Orhan Güzel",
      "commitHash": "8da4e9a8d6a12db1d202422029178363f046a7c0",
      "date": "2025-06-18T22:04:22.810Z",
      "note": "Meta versiyonu {version} olarak {by} tarafından yükseltildi."
    },
    {
      "version": "1.0.24",
      "by": "Orhan Güzel",
      "commitHash": "8da4e9a8d6a12db1d202422029178363f046a7c0",
      "date": "2025-06-19T00:11:38.673Z",
      "note": "Meta versiyonu {version} olarak {by} tarafından yükseltildi."
    },
    {
      "version": "1.0.25",
      "by": "Orhan Güzel",
      "commitHash": "8da4e9a8d6a12db1d202422029178363f046a7c0",
      "date": "2025-06-19T00:11:40.659Z",
      "note": "Meta versiyonu {version} olarak {by} tarafından yükseltildi."
    },
    {
      "version": "1.0.26",
      "by": "Orhan Güzel",
      "commitHash": "8da4e9a8d6a12db1d202422029178363f046a7c0",
      "date": "2025-06-19T00:11:50.591Z",
      "note": "Meta versiyonu {version} olarak {by} tarafından yükseltildi."
    },
    {
      "version": "1.0.27",
      "by": "Orhan Güzel",
      "commitHash": "8da4e9a8d6a12db1d202422029178363f046a7c0",
      "date": "2025-06-19T00:32:13.541Z",
      "note": "Meta versiyonu {version} olarak {by} tarafından yükseltildi."
    },
    {
      "version": "1.0.28",
      "by": "Orhan Güzel",
      "commitHash": "8da4e9a8d6a12db1d202422029178363f046a7c0",
      "date": "2025-06-19T00:32:15.979Z",
      "note": "Meta versiyonu {version} olarak {by} tarafından yükseltildi."
    },
    {
      "version": "1.0.29",
      "by": "Orhan Güzel",
      "commitHash": "8da4e9a8d6a12db1d202422029178363f046a7c0",
      "date": "2025-06-19T00:32:28.838Z",
      "note": "Meta versiyonu {version} olarak {by} tarafından yükseltildi."
    },
    {
      "version": "1.0.30",
      "by": "Orhan Güzel",
      "commitHash": "8da4e9a8d6a12db1d202422029178363f046a7c0",
      "date": "2025-06-19T01:22:57.549Z",
      "note": "Meta versiyonu {version} olarak {by} tarafından yükseltildi."
    },
    {
      "version": "1.0.31",
      "by": "Orhan Güzel",
      "commitHash": "8da4e9a8d6a12db1d202422029178363f046a7c0",
      "date": "2025-06-19T01:23:00.667Z",
      "note": "Meta versiyonu {version} olarak {by} tarafından yükseltildi."
    },
    {
      "version": "1.0.32",
      "by": "Orhan Güzel",
      "commitHash": "8da4e9a8d6a12db1d202422029178363f046a7c0",
      "date": "2025-06-19T01:23:19.149Z",
      "note": "Meta versiyonu {version} olarak {by} tarafından yükseltildi."
    },
    {
      "version": "1.0.33",
      "by": "Orhan Güzel",
      "commitHash": "8da4e9a8d6a12db1d202422029178363f046a7c0",
      "date": "2025-06-19T11:02:52.850Z",
      "note": "Meta versiyonu {version} olarak {by} tarafından yükseltildi."
    },
    {
      "version": "1.0.34",
      "by": "Orhan Güzel",
      "commitHash": "8da4e9a8d6a12db1d202422029178363f046a7c0",
      "date": "2025-06-19T11:02:55.143Z",
      "note": "Meta versiyonu {version} olarak {by} tarafından yükseltildi."
    },
    {
      "version": "1.0.35",
      "by": "Orhan Güzel",
      "commitHash": "8da4e9a8d6a12db1d202422029178363f046a7c0",
      "date": "2025-06-19T11:03:08.728Z",
      "note": "Meta versiyonu {version} olarak {by} tarafından yükseltildi."
    },
    {
      "version": "1.0.36",
      "by": "Orhan Güzel",
      "commitHash": "8da4e9a8d6a12db1d202422029178363f046a7c0",
      "date": "2025-06-19T11:07:12.470Z",
      "note": "Meta versiyonu {version} olarak {by} tarafından yükseltildi."
    },
    {
      "version": "1.0.37",
      "by": "Orhan Güzel",
      "commitHash": "8da4e9a8d6a12db1d202422029178363f046a7c0",
      "date": "2025-06-19T11:07:13.859Z",
      "note": "Meta versiyonu {version} olarak {by} tarafından yükseltildi."
    },
    {
      "version": "1.0.38",
      "by": "Orhan Güzel",
      "commitHash": "8da4e9a8d6a12db1d202422029178363f046a7c0",
      "date": "2025-06-19T11:07:24.193Z",
      "note": "Meta versiyonu {version} olarak {by} tarafından yükseltildi."
    },
    {
      "version": "1.0.39",
      "by": "Orhan Güzel",
      "commitHash": "8da4e9a8d6a12db1d202422029178363f046a7c0",
      "date": "2025-06-19T11:19:33.884Z",
      "note": "Meta versiyonu {version} olarak {by} tarafından yükseltildi."
    },
    {
      "version": "1.0.40",
      "by": "Orhan Güzel",
      "commitHash": "8da4e9a8d6a12db1d202422029178363f046a7c0",
      "date": "2025-06-19T11:19:35.519Z",
      "note": "Meta versiyonu {version} olarak {by} tarafından yükseltildi."
    },
    {
      "version": "1.0.41",
      "by": "Orhan Güzel",
      "commitHash": "8da4e9a8d6a12db1d202422029178363f046a7c0",
      "date": "2025-06-19T11:19:46.877Z",
      "note": "Meta versiyonu {version} olarak {by} tarafından yükseltildi."
    }
  ]
}